setup.py
tapioca_parse/__init__.py
tapioca_parse/resource_mapping.py
tapioca_parse/tapioca_parse.py
tapioca_parse.egg-info/PKG-INFO
tapioca_parse.egg-info/SOURCES.txt
tapioca_parse.egg-info/dependency_links.txt
tapioca_parse.egg-info/not-zip-safe
tapioca_parse.egg-info/requires.txt
tapioca_parse.egg-info/top_level.txt