Metadata-Version: 1.1
Name: tapioca-parse
Version: 0.2.0
Summary: Parse REST API wrapper using tapioca
Home-page: https://github.com/vintasoftware/tapioca-parse
Author: Filipe Ximenes
Author-email: filipeximenes@gmail.com
License: BSD
Keywords: parse,tapioca,wrapper,api
Platform: UNKNOWN
Classifier: Development Status :: 2 - Pre-Alpha
Classifier: Intended Audience :: Developers
Classifier: License :: OSI Approved :: BSD License
Classifier: Natural Language :: English
Classifier: Programming Language :: Python :: 2.7
